{"frames":[{"filename":"bubble_explo2","frame":{"x":0,"y":0,"w":32,"h":32},"rotated":false,"trimmed":false,"spriteSourceSize":{"x":0,"y":0,"w":32,"h":32},"sourceSize":{"w":32,"h":32}},{"filename":"bubble_explo3","frame":{"x":0,"y":33,"w":32,"h":32},"rotated":false,"trimmed":false,"spriteSourceSize":{"x":0,"y":0,"w":32,"h":32},"sourceSize":{"w":32,"h":32}},{"filename":"bubble_explo4","frame":{"x":33,"y":0,"w":32,"h":32},"rotated":false,"trimmed":false,"spriteSourceSize":{"x":0,"y":0,"w":32,"h":32},"sourceSize":{"w":32,"h":32}},{"filename":"bubble_explo5","frame":{"x":33,"y":33,"w":32,"h":32},"rotated":false,"trimmed":false,"spriteSourceSize":{"x":0,"y":0,"w":32,"h":32},"sourceSize":{"w":32,"h":32}},{"filename":"bubble_explo6","frame":{"x":0,"y":66,"w":32,"h":32},"rotated":false,"trimmed":false,"spriteSourceSize":{"x":0,"y":0,"w":32,"h":32},"sourceSize":{"w":32,"h":32}},{"filename":"bubble_explo7","frame":{"x":33,"y":66,"w":32,"h":32},"rotated":false,"trimmed":false,"spriteSourceSize":{"x":0,"y":0,"w":32,"h":32},"sourceSize":{"w":32,"h":32}},{"filename":"bubble_explo8","frame":{"x":66,"y":0,"w":32,"h":32},"rotated":false,"trimmed":false,"spriteSourceSize":{"x":0,"y":0,"w":32,"h":32},"sourceSize":{"w":32,"h":32}},{"filename":"bubble_explo9","frame":{"x":66,"y":33,"w":32,"h":32},"rotated":false,"trimmed":false,"spriteSourceSize":{"x":0,"y":0,"w":32,"h":32},"sourceSize":{"w":32,"h":32}},{"filename":"bubble_explo10","frame":{"x":66,"y":66,"w":32,"h":32},"rotated":false,"trimmed":false,"spriteSourceSize":{"x":0,"y":0,"w":32,"h":32},"sourceSize":{"w":32,"h":32}},{"filename":"bubble_explo1","frame":{"x":0,"y":99,"w":32,"h":32},"rotated":false,"trimmed":false,"spriteSourceSize":{"x":0,"y":0,"w":32,"h":32},"sourceSize":{"w":32,"h":32}}],"meta":{"app":"https://www.leshylabs.com/apps/sstool/","version":"Leshy SpriteSheet Tool v0.8.4","image":"explosion.png","size":{"w":98,"h":131},"scale":1}}